MANIFEST.in
README.txt
requirements.txt
setup.py
test_requirements.txt
version.txt
cloudshell/__init__.py
cloudshell/networking/__init__.py
cloudshell/networking/ericsson/__init__.py
cloudshell/networking/ericsson/seos/__init__.py
cloudshell/networking/ericsson/seos/ericsson_seos_configuration.py
cloudshell/networking/ericsson/seos/ericsson_seos_resource_driver.py
cloudshell/networking/ericsson/seos/autoload/__init__.py
cloudshell/networking/ericsson/seos/autoload/ericsson_seos_snmp_autoload.py
cloudshell/networking/ericsson/seos/autoload/mib/RBN-IP-BIND-MIB.py
cloudshell/networking/ericsson/seos/autoload/mib/RBN-PRODUCT-MIB.py
cloudshell/networking/ericsson/seos/autoload/mib/RBN-SMI.py
cloudshell/networking/ericsson/seos/autoload/mib/RBN-TC.py
cloudshell/networking/ericsson/seos/autoload/mib/__init__.py
cloudshell_networking_ericsson_seos.egg-info/PKG-INFO
cloudshell_networking_ericsson_seos.egg-info/SOURCES.txt
cloudshell_networking_ericsson_seos.egg-info/dependency_links.txt
cloudshell_networking_ericsson_seos.egg-info/requires.txt
cloudshell_networking_ericsson_seos.egg-info/top_level.txt