Metadata-Version: 1.0
Name: cloudshell-networking-ericsson-seos
Version: 1.0.25
Summary: QualiSystems networking Ericsson SEOS specific Package
Home-page: http://www.qualisystems.com/
Author: QualiSystems
Author-email: info@qualisystems.com
License: UNKNOWN
Platform: UNKNOWN
